doc2docx/__init__.py
doc2docx/convert.jxa
doc2docx-0.2.4.dist-info/LICENSE
doc2docx-0.2.4.dist-info/METADATA
doc2docx-0.2.4.dist-info/WHEEL
doc2docx-0.2.4.dist-info/entry_points.txt
doc2docx-0.2.4.dist-info/RECORD
