Metadata-Version: 2.1
Name: doc2docx
Version: 0.2.4
Summary: Convert doc to docx on Windows or macOS directly using Microsoft Word (must be installed).
Home-page: https://github.com/cosmojg/doc2docx
License: MIT
Author: Cosmo
Author-email: cosmo@cosmo.red
Requires-Python: >=3.9,<4.0
Classifier: Environment :: MacOS X
Classifier: Environment :: Win32 (MS Windows)
Classifier: License :: OSI Approved :: MIT License
Classifier: Operating System :: MacOS
Classifier: Operating System :: Microsoft :: Windows
Classifier: Programming Language :: Python :: 3
Classifier: Programming Language :: Python :: 3.9
Classifier: Programming Language :: Python :: 3.10
Classifier: Programming Language :: Python :: 3.11
Classifier: Topic :: Office/Business :: Office Suites
Classifier: Topic :: Software Development :: Libraries
Requires-Dist: appscript (>=1.2.2,<2.0.0) ; sys_platform == "darwin"
Requires-Dist: pywin32 (>=305,<306) ; sys_platform == "win32"
Requires-Dist: tqdm (>=4.65.0,<5.0.0)
Project-URL: Repository, https://github.com/cosmojg/doc2docx
